{
    "heading": "offers, deals and coupons",
    "description": "we have the best offers and deals to help you save money online on everything you buy or book. at this section of our website, you will get the latest and exciting discount coupon codes. so next time to you are on a holiday or for some business work, do not forget to check out this page for much more marvelous options.",
    "content": {
        "action": [
            {
                "key": "filter by",
                "operations": [
                    "view all",
                    "hotel",
                    "entertainment",
                    "restaurant",
                    "wedding"
                ]
            },
            {
                "key": "change view",
                "operations": [
                    "fas fa-grip-horizontal",
                    "fas fa-grip-vertical"
                ]
            }
        ],
        "coupons": [
            {
                "type": "hotel",
                "path": "../../assets/images/offers/room-discount.jpg",
                "icon": "fas fa-bed",
                "heading": "flat 10% off on room booking",
                "description": "now you can get flat 10% off on domestic hotel room booking at bourbon bliss. this offer only applicable room's booking.",
                "currency": "rs.",
                "price": 1000,
                "discount": {
                    "type": "promo code",
                    "code": "room5673"
                },
                "eligibility": [
                    {
                        "key": "min. booking amount",
                        "amount": 1000
                    },
                    {
                        "key": "max. amount can be availed",
                        "amount": 5000
                    }
                ],
                "duration": {
                    "key": "validity till",
                    "date": "12-07-2019"
                }
            },
            {
                "type": "hotel",
                "path": "../../assets/images/offers/suite-discount.jpg",
                "icon": "fas fa-gem",
                "heading": "50% discount on executive suite",
                "description": "now avail exclusive 50% off on all executive and deluxe suites across india only at bourbon bliss.",
                "currency": "rs.",
                "price": 1000,
                "discount": {
                    "type": "promo code",
                    "code": "suit3210"
                },
                "eligibility": [
                    {
                        "key": "min. booking amount",
                        "amount": 2000
                    },
                    {
                        "key": "max. amount can be availed",
                        "amount": 10000
                    }
                ],
                "duration": {
                    "key": "validity till",
                    "date": "11-03-2019"
                }
            },
            {
                "type": "hotel",
                "path": "../../assets/images/offers/seaview-discount.jpg",
                "icon": "fas fa-umbrella-beach",
                "heading": "festive sale – upto 1500 off on seaview rooms",
                "description": "get upto rs. 1500 off on seaview hotel rooms, holiday package booking across country.",
                "currency": "rs.",
                "price": 1000,
                "discount": {
                    "type": "promo code",
                    "code": "seav2963"
                },
                "eligibility": [
                    {
                        "key": "min. booking amount",
                        "amount": 800
                    },
                    {
                        "key": "max. amount can be availed",
                        "amount": 1500
                    }
                ],
                "duration": {
                    "key": "validity till",
                    "date": "11-04-2019"
                }
            },
            {
                "type": "hotel",
                "path": "../../assets/images/offers/last-minute-booking.jpg",
                "icon": "fas fa-clock",
                "heading": "last minute deal – upto 30% off",
                "description": "now you can save extra payment on last minute deals and get upto flat 30% off on hotel bookings.",
                "currency": "rs.",
                "price": 1000,
                "discount": {
                    "type": "promo code",
                    "code": "last1200"
                },
                "eligibility": [
                    {
                        "key": "min. booking amount",
                        "amount": 0
                    },
                    {
                        "key": "max. amount can be availed",
                        "amount": 0
                    }
                ],
                "duration": {
                    "key": "validity till",
                    "date": "22-02-2019"
                }
            },
            {
                "type": "entertainment",
                "path": "../../assets/images/offers/paytm-movie-discount.jpg",
                "icon": "fas fa-film",
                "heading": "flat rs. 100 cashback on paytm",
                "description": "book movie tickets using paytm and get instant cashback in your paytm wallet. this offer is valid for a limited period only.",
                "currency": "rs.",
                "price": 500,
                "discount": {
                    "type": "promo code",
                    "code": "payt0845"
                },
                "eligibility": [
                    {
                        "key": "for booking on paytm.com and paytm app"
                    },
                    {
                        "key": "amount credited within 24 hours"
                    }
                ],
                "duration": {
                    "key": "validity till",
                    "date": "20-03-2019"
                }
            },
            {
                "type": "entertainment",
                "path": "../../assets/images/offers/buy-one-get-one.jpg",
                "icon": "fas fa-film",
                "heading": "buy one get one offer",
                "description": "buy any movie ticket using lakshmi vilas bank debit / credit card and get another ticket absolutely free.",
                "currency": "rs.",
                "price": 500,
                "discount": {
                    "type": "promo code",
                    "code": "buyg1764"
                },
                "eligibility": [
                    {
                        "key": "min. booking amount: rs. 500"
                    },
                    {
                        "key": "ticket should be collected at the theatre"
                    }
                ],
                "duration": {
                    "key": "validity till",
                    "date": "not applicable"
                }
            },
            {
                "type": "entertainment",
                "path": "../../assets/images/offers/icici-movie-discount.jpg",
                "icon": "fas fa-film",
                "heading": "free movie ticket on every moonth",
                "description": "get upto 5 tickets of your favourite and latest movies on every month with icici bank debit card only.",
                "currency": "rs.",
                "price": 1500,
                "discount": {
                    "type": "promo code",
                    "code": "icic4372"
                },
                "eligibility": [
                    {
                        "key": "min. booking amount: rs. 1500"
                    },
                    {
                        "key": "max. no. of booking: 5 per month"
                    }
                ],
                "duration": {
                    "key": "validity",
                    "date": "1 month"
                }
            },
            {
                "type": "entertainment",
                "path": "../../assets/images/offers/last-minute-cancellation.jpg",
                "icon": "fas fa-film",
                "heading": "last minute cancellation",
                "description": "last minute change in plans? rohini silver screens offer you movie ticket cancellation in association with bookmyshow.",
                "currency": "rs.",
                "price": 500,
                "discount": {
                    "type": "promo code",
                    "code": "last2409"
                },
                "eligibility": [
                    {
                        "key": "applicable only for rohini screens"
                    },
                    {
                        "key": "amount will be credited to bank account"
                    }
                ],
                "duration": {
                    "key": "validity",
                    "date": "not applicable"
                }
            },
            {
                "type": "restaurant",
                "path": "../../assets/images/offers/zomato-discount.jpg",
                "icon": "fas fa-utensils",
                "heading": "flat 50% off on online booking",
                "description": "zomato offers flat 50% discount on any food orders online exclusively for you. grab this offer immediately.",
                "currency": "rs.",
                "price": 1000,
                "discount": {
                    "type": "promo code",
                    "code": "zoma8742"
                },
                "eligibility": [
                    {
                        "key": "min. booking amount",
                        "amount": 0
                    },
                    {
                        "key": "max. amount can be availed",
                        "amount": 500
                    }
                ],
                "duration": {
                    "key": "validity till",
                    "date": "01-03-2019"
                }
            },
            {
                "type": "restaurant",
                "path": "../../assets/images/offers/last-minute-cancellation.jpg",
                "icon": "fas fa-utensils",
                "heading": "",
                "description": "",
                "currency": "rs.",
                "price": 1000,
                "discount": {
                    "type": "promo code",
                    "code": ""
                },
                "eligibility": [
                    {
                        "key": "min. booking amount",
                        "amount": 1000
                    },
                    {
                        "key": "max. amount can be availed",
                        "amount": 1000
                    }
                ],
                "duration": {
                    "key": "validity till",
                    "date": ""
                }
            },
            {
                "type": "restaurant",
                "path": "../../assets/images/offers/last-minute-cancellation.jpg",
                "icon": "fas fa-utensils",
                "heading": "",
                "description": "",
                "currency": "rs.",
                "price": 1000,
                "discount": {
                    "type": "promo code",
                    "code": ""
                },
                "eligibility": [
                    {
                        "key": "min. booking amount",
                        "amount": 1000
                    },
                    {
                        "key": "max. amount can be availed",
                        "amount": 1000
                    }
                ],
                "duration": {
                    "key": "validity till",
                    "date": ""
                }
            },
            {
                "type": "restaurant",
                "path": "../../assets/images/offers/last-minute-cancellation.jpg",
                "icon": "fas fa-utensils",
                "heading": "",
                "description": "",
                "currency": "rs.",
                "price": 1000,
                "discount": {
                    "type": "promo code",
                    "code": ""
                },
                "eligibility": [
                    {
                        "key": "min. booking amount",
                        "amount": 1000
                    },
                    {
                        "key": "max. amount can be availed",
                        "amount": 1000
                    }
                ],
                "duration": {
                    "key": "validity till",
                    "date": ""
                }
            },
            {
                "type": "wedding",
                "path": "",
                "icon": "",
                "heading": "",
                "description": "",
                "currency": "rs.",
                "price": 1000,
                "discount": {
                    "type": "promo code",
                    "code": ""
                },
                "eligibility": [
                    {
                        "key": "min. booking amount",
                        "amount": 1000
                    },
                    {
                        "key": "max. amount can be availed",
                        "amount": 1000
                    }
                ],
                "duration": {
                    "key": "validity till",
                    "date": ""
                }
            },
            {
                "type": "wedding",
                "path": "",
                "icon": "",
                "heading": "",
                "description": "",
                "currency": "rs.",
                "price": 1000,
                "discount": {
                    "type": "promo code",
                    "code": ""
                },
                "eligibility": [
                    {
                        "key": "min. booking amount",
                        "amount": 1000
                    },
                    {
                        "key": "max. amount can be availed",
                        "amount": 1000
                    }
                ],
                "duration": {
                    "key": "validity till",
                    "date": ""
                }
            },
            {
                "type": "wedding",
                "path": "",
                "icon": "",
                "heading": "",
                "description": "",
                "currency": "rs.",
                "price": 1000,
                "discount": {
                    "type": "promo code",
                    "code": ""
                },
                "eligibility": [
                    {
                        "key": "min. booking amount",
                        "amount": 1000
                    },
                    {
                        "key": "max. amount can be availed",
                        "amount": 1000
                    }
                ],
                "duration": {
                    "key": "validity till",
                    "date": ""
                }
            },
            {
                "type": "wedding",
                "path": "",
                "icon": "",
                "heading": "",
                "description": "",
                "currency": "rs.",
                "price": 1000,
                "discount": {
                    "type": "promo code",
                    "code": ""
                },
                "eligibility": [
                    {
                        "key": "min. booking amount",
                        "amount": 1000
                    },
                    {
                        "key": "max. amount can be availed",
                        "amount": 1000
                    }
                ],
                "duration": {
                    "key": "validity till",
                    "date": ""
                }
            }
        ]
    }
}